smaca/__init__.py
smaca/bam.py
smaca/cli.py
smaca/constants.py
smaca/sma.py
smaca/test_results.py
smaca/utils.py
smaca/data/.gitignore
smaca/data/151002_7001448_0359_AC7F6GANXX_Sample_HG002-EEogPU_v02-KIT-Av5_AGATGTAC_L008.posiSrt.markDup.includedRegions.bam
smaca/data/151002_7001448_0359_AC7F6GANXX_Sample_HG002-EEogPU_v02-KIT-Av5_AGATGTAC_L008.posiSrt.markDup.includedRegions.bam.bai
smaca/data/HG007.GRCh38_full_plus_hs38d1_analysis_set_minus_alts.100x.includedRegions.downSampled.bam
smaca/data/HG007.GRCh38_full_plus_hs38d1_analysis_set_minus_alts.100x.includedRegions.downSampled.bam.bai
smaca/data/HG007.hs37d5.100x.includedRegions.downSampled.bam
smaca/data/HG007.hs37d5.100x.includedRegions.downSampled.bam.bai
smaca/data/included_regions_hg19.bed
smaca/data/included_regions_hg38.bed
smaca/data/included_regions_hs37d5.bed
smaca/data/output.csv
smaca/data/output_par.csv
smaca/data/output_ser.csv
smaca-1.2.3.dist-info/LICENSE.txt
smaca-1.2.3.dist-info/METADATA
smaca-1.2.3.dist-info/WHEEL
smaca-1.2.3.dist-info/entry_points.txt
smaca-1.2.3.dist-info/top_level.txt
smaca-1.2.3.dist-info/RECORD
