Metadata-Version: 2.1
Name: smaca
Version: 1.2.3
Summary: UNKNOWN
Home-page: https://github.com/babelomics/SMAca
Author: Daniel López López, Carlos Loucera
Author-email: daniel.lopez.lopez@juntadeandalucia.es, carlos.loucera@juntadeandalucia.es
License: GNU General Public License v.3.0
Platform: UNKNOWN
Requires-Python: >=3.6
Requires-Dist: click
Requires-Dist: cython
Requires-Dist: numpy
Requires-Dist: pysam
Requires-Dist: joblib
